cuba_weather_redcuba/__init__.py
cuba_weather_redcuba/data_providers/__init__.py
cuba_weather_redcuba/data_providers/sources.py
cuba_weather_redcuba/data_providers/weather_api_client.py
cuba_weather_redcuba/models/__init__.py
cuba_weather_redcuba/models/source_model.py
cuba_weather_redcuba/models/weather_model.py
cuba_weather_redcuba/repositories/__init__.py
cuba_weather_redcuba/repositories/source_repository.py
cuba_weather_redcuba/repositories/weather_repository.py
cuba_weather_redcuba/utils/__init__.py
cuba_weather_redcuba/utils/damerau_levenshtein.py
cuba_weather_redcuba/utils/exceptions.py
cuba_weather_redcuba-0.0.11.dist-info/LICENSE
cuba_weather_redcuba-0.0.11.dist-info/METADATA
cuba_weather_redcuba-0.0.11.dist-info/WHEEL
cuba_weather_redcuba-0.0.11.dist-info/top_level.txt
cuba_weather_redcuba-0.0.11.dist-info/RECORD
