Metadata-Version: 2.1
Name: cuba-weather-redcuba
Version: 0.0.11
Summary: Python3 client for (https://www.redcuba.cu) weather API
Home-page: https://github.com/cuba-weather/cuba-weather-redcuba-python
Author: Cuban Open Source Community
License: MIT
Platform: UNKNOWN
Classifier: Programming Language :: Python :: 3
Classifier: License :: OSI Approved :: MIT License
Classifier: Operating System :: OS Independent
Requires-Python: >=3.6
Requires-Dist: cuba-weather-municipality
